llm_fragments_sourcehut.py
llm_fragments_sourcehut-0.1.3.dist-info/licenses/LICENSE
llm_fragments_sourcehut-0.1.3.dist-info/METADATA
llm_fragments_sourcehut-0.1.3.dist-info/WHEEL
llm_fragments_sourcehut-0.1.3.dist-info/entry_points.txt
llm_fragments_sourcehut-0.1.3.dist-info/top_level.txt
llm_fragments_sourcehut-0.1.3.dist-info/RECORD
